GoBianchengShiguangFix1/README.md
GoBianchengShiguangFix1/__init__.py
GoBianchengShiguangFix1/__main__.py
GoBianchengShiguangFix1/file.epub
GoBianchengShiguangFix1/index.html
GoBianchengShiguangFix1/css/__init__.py
GoBianchengShiguangFix1/css/annotations.css
GoBianchengShiguangFix1/css/main.css
GoBianchengShiguangFix1/css/normalize.css
GoBianchengShiguangFix1/css/popup.css
GoBianchengShiguangFix1/font/__init__.py
GoBianchengShiguangFix1/font/fontello.eot
GoBianchengShiguangFix1/font/fontello.svg
GoBianchengShiguangFix1/font/fontello.ttf
GoBianchengShiguangFix1/font/fontello.woff
GoBianchengShiguangFix1/img/__init__.py
GoBianchengShiguangFix1/img/annotator-glyph-sprite.png
GoBianchengShiguangFix1/img/annotator-icon-sprite.png
GoBianchengShiguangFix1/img/apple-touch-icon.png
GoBianchengShiguangFix1/img/cancelfullscreen.png
GoBianchengShiguangFix1/img/close.png
GoBianchengShiguangFix1/img/fullscreen.png
GoBianchengShiguangFix1/img/loader.gif
GoBianchengShiguangFix1/img/menu-icon.png
GoBianchengShiguangFix1/img/save.png
GoBianchengShiguangFix1/img/saved.png
GoBianchengShiguangFix1/img/settings-s.png
GoBianchengShiguangFix1/img/settings.png
GoBianchengShiguangFix1/img/star.png
GoBianchengShiguangFix1/js/__init__.py
GoBianchengShiguangFix1/js/epub.js
GoBianchengShiguangFix1/js/epub.min.js
GoBianchengShiguangFix1/js/epub.min.map
GoBianchengShiguangFix1/js/hooks.min.js
GoBianchengShiguangFix1/js/hooks.min.map
GoBianchengShiguangFix1/js/reader.js
GoBianchengShiguangFix1/js/reader.js.map
GoBianchengShiguangFix1/js/reader.min.js
GoBianchengShiguangFix1/js/reader.min.map
GoBianchengShiguangFix1/js/hooks/__init__.py
GoBianchengShiguangFix1/js/hooks/extensions/__init__.py
GoBianchengShiguangFix1/js/hooks/extensions/highlight.js
GoBianchengShiguangFix1/js/libs/__init__.py
GoBianchengShiguangFix1/js/libs/jquery.min.js
GoBianchengShiguangFix1/js/libs/localforage.min.js
GoBianchengShiguangFix1/js/libs/screenfull.js
GoBianchengShiguangFix1/js/libs/screenfull.min.js
go_biancheng_shiguang_fix1-2025.3.25.1.dist-info/METADATA
go_biancheng_shiguang_fix1-2025.3.25.1.dist-info/WHEEL
go_biancheng_shiguang_fix1-2025.3.25.1.dist-info/entry_points.txt
go_biancheng_shiguang_fix1-2025.3.25.1.dist-info/top_level.txt
go_biancheng_shiguang_fix1-2025.3.25.1.dist-info/RECORD
